fbdev/__init__.py
fbdev/_modidx.py
fbdev/_utils/__init__.py
fbdev/_utils/attr_container.py
fbdev/_utils/events.py
fbdev/_utils/misc.py
fbdev/_utils/states.py
fbdev/_utils/task_manager.py
fbdev/_utils.py
fbdev/comp/__init__.py
fbdev/comp/base_component.py
fbdev/comp/packet.py
fbdev/comp/port.py
fbdev/complib/__init__.py
fbdev/complib/exec_component.py
fbdev/complib/func_component_factory.py
fbdev/complib/job_handler_factory.py
fbdev/concurrent/__init__.py
fbdev/concurrent/remote.py
fbdev/concurrent/subprocess_node_launcher.py
fbdev/dev_utils.py
fbdev/exceptions.py
fbdev/graph/__init__.py
fbdev/graph/_utils/__init__.py
fbdev/graph/_utils/graph_spec_to_mermaid.py
fbdev/graph/_utils/node_lookup_by_address.py
fbdev/graph/graph_component.py
fbdev/graph/graph_spec.py
fbdev/graph/net.py
fbdev/graph/packet_registry.py
fbdev/runtime/__init__.py
fbdev/runtime/_utils.py
fbdev/runtime/base_runtime.py
fbdev/runtime/batch_executor.py
fbdev/runtime/node_process.py
fbdev-0.0.5.dist-info/LICENSE
fbdev-0.0.5.dist-info/METADATA
fbdev-0.0.5.dist-info/WHEEL
fbdev-0.0.5.dist-info/RECORD
